{"ziadatel":{"ziatetelTyp":true},"ziadatelUdaje":{"nazov":"Extropy","sidlo":"qui","mesto":"NNxWcqtF","psc":"cillum","ico":"veniam pariatur","banka":"labore magna","iban":"dolor et sit quis","menoPriezvisko":"in","email":"zptp8PGg7kJZr@lYcSrTmbqeFGEVapzmFNMTN.qpm","telefon":"+8"},"typStanovista":{"typStanovistaUpresnenie":"Nahradenie existujúceho stanovišťa"},"stanovisteInformacie":{"mestomPonukanaDokumentacia":false,"popisZbernychNadob":"dolor quis","vegetacnaStrecha":false,"vegetacnaStena":false,"sadoveUpravy":false},"miestoUmiestnenia":{"kataster":["enim","labore Ut sint"],"parcela":"n","adresaUmiestnenia":["sit consectetur nisi commodo et"],"velkost":88248525.11835024},"dovodZiadosti":{"zaujem":"Dotáciu na kontajnerové stojisko"},"zmluva":["9zwT2KCYDLY.hbO"],"snimkaZMapy":["9sgudxG5.qVr","CjZ5wSy.rVO","79XCPX.Vig","VWcKdP.oaX"],"podorysStanovista":["8ULpkLtr.ByJ","Si,OXEEG.UTC","lRUt4tvwQ8j.uHK","_gGAQ.FYo"],"vizualStanovista":["2R.xfB","PnNF8d.BlS"],"technickyVykres":{"technickyVykresText":"dolore laborum"},"stavebnaDokumentacia":["oY28Rkw8exf.Iqv","M_.tCd","5QfvyNDn2.cWa"," ,ClXgrRC.IsJ"],"rozpocet":{"rozpocetPrilohy":["PnRx9yMo.zQP","a.BPR","N.OUx","z8.Fes"]},"inePrilohy":["MG-.Kpl","sIdsbKmh8Zv.jrZ","IT55mZ5Sjn.icl","J.QQo"]}